acquisition_decisions_sc/__init__.py
acquisition_decisions_sc/__main__.py
acquisition_decisions_sc/__main__.py.2fea474d3cc0366a5abe8a23fc529e3e.tmp
acquisition_decisions_sc/annex/__init__.py
acquisition_decisions_sc/annex/divider.py
acquisition_decisions_sc/annex/extra.py
acquisition_decisions_sc/annex/gist.py
acquisition_decisions_sc/field/__init__.py
acquisition_decisions_sc/field/body.py
acquisition_decisions_sc/field/category.py
acquisition_decisions_sc/field/composition.py
acquisition_decisions_sc/field/writer.py
acquisition_decisions_sc/ponencia/__init__.py
acquisition_decisions_sc/ponencia/dissect.py
acquisition_decisions_sc/ponencia/format.py
acquisition_decisions_sc/ponencia/slice.py
acquisition_decisions_sc/utils.py
acquisition_decisions_sc-0.0.2.dist-info/WHEEL
acquisition_decisions_sc-0.0.2.dist-info/METADATA
acquisition_decisions_sc-0.0.2.dist-info/RECORD
